ansible_autodoc-0.5.3.data/scripts/ansible-autodoc
ansibleautodoc/Annotation.py
ansibleautodoc/AutodocCli.py
ansibleautodoc/Config.py
ansibleautodoc/Contstants.py
ansibleautodoc/DocumentationGenerator.py
ansibleautodoc/DocumentationParser.py
ansibleautodoc/FileRegistry.py
ansibleautodoc/Utils.py
ansibleautodoc/__init__.py
ansibleautodoc/templates/cliprint/_action.j2
ansibleautodoc/templates/cliprint/_description.j2
ansibleautodoc/templates/cliprint/_tags.j2
ansibleautodoc/templates/cliprint/_todo.j2
ansibleautodoc/templates/cliprint/_var.j2
ansibleautodoc/templates/cliprint/print_to_cli.j2
ansibleautodoc/templates/doc_and_readme/README.md.j2
ansibleautodoc/templates/doc_and_readme/_example.j2
ansibleautodoc/templates/doc_and_readme/doc/_action.j2
ansibleautodoc/templates/doc_and_readme/doc/_tags.j2
ansibleautodoc/templates/doc_and_readme/doc/report.md.j2
ansibleautodoc/templates/doc_and_readme/doc/tags.md.j2
ansibleautodoc/templates/doc_and_readme/doc/todo.md.j2
ansibleautodoc/templates/doc_and_readme/doc/variables.md.j2
ansibleautodoc/templates/readme/README.md.j2
ansibleautodoc/templates/readme/_action.j2
ansibleautodoc/templates/readme/_dev_var_dump.txt.j2
ansibleautodoc/templates/readme/_example.j2
ansibleautodoc/templates/readme/_tags.j2
ansibleautodoc/templates/readme/_todo.j2
ansibleautodoc/templates/readme/_vars.j2
ansible_autodoc-0.5.3.dist-info/LICENSE
ansible_autodoc-0.5.3.dist-info/METADATA
ansible_autodoc-0.5.3.dist-info/WHEEL
ansible_autodoc-0.5.3.dist-info/top_level.txt
ansible_autodoc-0.5.3.dist-info/RECORD
